<?xml version='1.0' encoding='UTF-8'?>
<com.dabsquared.gitlabjenkins.connection.GitLabConnectionConfig plugin="gitlab-plugin@1.2.2">
  <connections>
    <com.dabsquared.gitlabjenkins.connection.GitLabConnection>
      <name></name>
      <url></url>
      <apiTokenId>c0349dcc-4399-4f60-9449-7a7dc6329168</apiTokenId>
      <ignoreCertificateErrors>false</ignoreCertificateErrors>
    </com.dabsquared.gitlabjenkins.connection.GitLabConnection>
  </connections>
</com.dabsquared.gitlabjenkins.connection.GitLabConnectionConfig>